CHANGELOG.rst
LICENSE
pytest_localstack/__init__.py
pytest_localstack/constants.py
pytest_localstack/container.py
pytest_localstack/contrib/__init__.py
pytest_localstack/contrib/boto3.py
pytest_localstack/contrib/botocore.py
pytest_localstack/exceptions.py
pytest_localstack/hookspecs.py
pytest_localstack/plugin.py
pytest_localstack/service_checks.py
pytest_localstack/session.py
pytest_localstack/utils.py
pytest_localstack-0.6.1.dist-info/entry_points.txt
pytest_localstack-0.6.1.dist-info/LICENSE
pytest_localstack-0.6.1.dist-info/WHEEL
pytest_localstack-0.6.1.dist-info/METADATA
pytest_localstack-0.6.1.dist-info/RECORD
