Metadata-Version: 2.1
Name: pytest-localstack
Version: 0.6.1
Summary: Pytest plugin for AWS integration tests
Home-page: https://github.com/mintel/pytest-localstack
License: MIT
Keywords: pytest,localstack,aws
Author: Mintel Group Ltd.
Requires-Python: >=3.7.0,<4.0.0
Classifier: Development Status :: 4 - Beta
Classifier: Framework :: Pytest
Classifier: Intended Audience :: Developers
Classifier: License :: OSI Approved :: MIT License
Classifier: Operating System :: POSIX
Classifier: Operating System :: Unix
Classifier: Programming Language :: Python
Classifier: Programming Language :: Python :: 3
Classifier: Programming Language :: Python :: 3.7
Classifier: Programming Language :: Python :: 3.8
Classifier: Programming Language :: Python :: 3.9
Classifier: Programming Language :: Python :: 3.10
Classifier: Programming Language :: Python :: 3.11
Classifier: Programming Language :: Python :: 3
Classifier: Programming Language :: Python :: 3.6
Classifier: Programming Language :: Python :: 3.7
Classifier: Programming Language :: Python :: 3.8
Classifier: Topic :: Software Development :: Libraries
Classifier: Topic :: Software Development :: Testing
Classifier: Topic :: Utilities
Requires-Dist: botocore (!=1.4.45)
Requires-Dist: docker (>=6.0.0,<7.0.0)
Requires-Dist: pluggy (>=0.12.0,<0.13.0)
Requires-Dist: pytest (>=6.0.0,<7.0.0)
Requires-Dist: urllib3 (<2)
Project-URL: Documentation, https://pytest-localstack.readthedocs.io/
Project-URL: Repository, https://github.com/mintel/pytest-localstack
